MANIFEST.in
README.rst
setup.py
pytimeextractor/__init__.py
pytimeextractor/config.py
pytimeextractor/extractor.py
pytimeextractor/timeextractor-jar-with-dependencies.jar
pytimeextractor.egg-info/PKG-INFO
pytimeextractor.egg-info/SOURCES.txt
pytimeextractor.egg-info/dependency_links.txt
pytimeextractor.egg-info/not-zip-safe
pytimeextractor.egg-info/requires.txt
pytimeextractor.egg-info/top_level.txt