Metadata-Version: 1.0
Name: pytimeextractor
Version: 0.1.1
Summary: Time Extractor NLP project - locate dates and times in text documents
Home-page: https://github.com/digamma-ai/timeextractor
Author: Digamma.ai
Author-email: info@digamma.ai
License: MIT
Keywords: NLP text extraction time date
Platform: UNKNOWN
